{
  "$schema": "https://ui.shadcn.com/schema/registry-item.json",
  "name": "kbd-02",
  "title": "KBD 02 - KBD Group",
  "description": "KbdGroup showcasing grouped multi-key shortcut combinations with Mac/Windows platform switch",
  "dependencies": [],
  "registryDependencies": [
    "kbd",
    "switch"
  ],
  "files": [
    {
      "path": "src/components/shadcn-space/kbd/kbd-02.tsx",
      "content": "'use client'\n\nimport { useState } from 'react'\nimport { Kbd, KbdGroup } from '@/components/ui/kbd'\nimport { Switch } from '@/components/ui/switch'\n\ntype Platform = 'mac' | 'win'\n\nconst KbdGroupDemo = () => {\n  const [platform, setPlatform] = useState<Platform>('mac')\n  const isMac = platform === 'mac'\n\n  return (\n    <div className=\"flex flex-col gap-4\">\n      {/* Platform switch */}\n      <div className=\"flex items-center gap-2 text-sm\">\n        <span className=\"text-muted-foreground\">MacOS</span>\n        <Switch\n          checked={platform === 'win'}\n          onCheckedChange={(checked) => setPlatform(checked ? 'win' : 'mac')}\n        />\n        <span className=\"text-muted-foreground\">Windows</span>\n      </div>\n\n      {/* Shortcuts */}\n      <div className=\"flex flex-col gap-3\">\n        <div className=\"flex items-center justify-between gap-4\">\n          <span className=\"text-sm text-muted-foreground\">Command Palette</span>\n          <KbdGroup>\n            <Kbd>{isMac ? '⌘' : 'Ctrl'}</Kbd>\n            <Kbd>{isMac ? '⇧' : 'Shift'}</Kbd>\n            <Kbd>P</Kbd>\n          </KbdGroup>\n        </div>\n\n        <div className=\"flex items-center justify-between gap-4\">\n          <span className=\"text-sm text-muted-foreground\">Find & Replace</span>\n          <KbdGroup>\n            <Kbd>{isMac ? '⌘' : 'Ctrl'}</Kbd>\n            <Kbd>{isMac ? '⇧' : 'Shift'}</Kbd>\n            <Kbd>H</Kbd>\n          </KbdGroup>\n        </div>\n\n        <div className=\"flex items-center justify-between gap-4\">\n          <span className=\"text-sm text-muted-foreground\">New Terminal</span>\n          <KbdGroup>\n            <Kbd>{isMac ? '⌘' : 'Ctrl'}</Kbd>\n            <Kbd>{isMac ? '⇧' : 'Shift'}</Kbd>\n            <Kbd>`</Kbd>\n          </KbdGroup>\n        </div>\n      </div>\n    </div>\n  )\n}\n\nexport default KbdGroupDemo\n",
      "type": "registry:component",
      "target": "components/shadcn-space/kbd/kbd-02.tsx"
    }
  ],
  "type": "registry:component"
}